<text xmlns="http://www.tei-c.org/ns/1.0"><body><div ana="#first-interview" decls="#first-interview"><p><pb facs="#f052"/>et quel polesene tra il faretto et la sabionera del bastion è successo per esser stata levata la <rs ref="#rs-pl">Brenta</rs>, perché quando l’acqua ›vegniva‹ della <rs ref="#rs-pl">Brenta</rs> vegniva la tegniva el sabbion spento alla riva ma dopo levata il sabion è venuto nel <rs ref="#rs-ne">canal</rs> et ha causato quell’alterratione ; anco in diversi altri luochi s’è alterrato come in <rs ref="#rs-pl">Melison</rs>, in <rs ref="#rs-pl">Navagiosa</rs> et altri luochi et questo è successo per la <rs ref="#rs-pl">Brenta</rs> et anco quei tagli con le sue scolladori menano del sporchezzo et quando l’acqua vien fuora d’essi la se perdi per la <rs ref="#rs-ne">laguna</rs> perché non vi è forza da condurla a basso». E domandato: «Che cosa per opinion vostra si potria far per rimediar a questi danni?». Rispose: «Io credo che si stenteria a rimediarvi». Rispose: «Che tornasse la <rs ref="#rs-pl">Brenta</rs> la portaria via qualche cosa et con il tempo la portaria forse ogni cosa, ma certo le tegniria che non si alterreria più per la rason del corso et di quel che ho detto di sopra». E domandato: «Chi facesse un <rs ref="#rs-ne">canale</rs>  nel <rs ref="#rs-gd">palude</rs> che conducesse <rs ref="#rs-ne">le acque del Laronzelo</rs> et altre dove capitava la <rs ref="#rs-pl">Brenta</rs>, credete che sivenisse a giovar alla <rs ref="#rs-ne">laguna</rs> et porto?». ‹ rispose › «Le fariano qualche benefitio ma non simile alla <rs ref="#rs-pl">Brenta</rs> perché la <rs ref="#rs-pl">Brenta</rs> è  <rs ref="#rs-gd">acqua viva</rs> / succia». E domandato: «Date qualche informatione del stato del <rs ref="#rs-pl">porto di Malamoco</rs>». Rispose: «Non so più che dire poiché ho detto et reccordato anco in scrittura molte cose insieme con mio</p></div></body></text>